Super_lux_library/__init__.py
Super_lux_library/jsonLib.py
Super_lux_library/osLib.py
Super_lux_library/randomLib.py
Super_lux_library/startLib.py
Super_lux_library/timeLib.py
Super_lux_library/turtleLib.py
super_lux_library-1.1.0.dist-info/METADATA
super_lux_library-1.1.0.dist-info/WHEEL
super_lux_library-1.1.0.dist-info/top_level.txt
super_lux_library-1.1.0.dist-info/RECORD
