Metadata-Version: 2.4
Name: Super_lux_library
Version: 1.1.0
Summary: Ziad Library for drawing, timers and random and more. Enjoy! if you new use start() after the import!!
Author: zeyad
Author-email: zeyad <zayedzezo82@gmail.com>
Requires-Python: >=3.7
Dynamic: author
